MANIFEST.in
README.md
requirements.txt
setup.py
pycartan/__init__.py
pycartan/core.py
pycartan/release.py
pycartan.egg-info/PKG-INFO
pycartan.egg-info/SOURCES.txt
pycartan.egg-info/dependency_links.txt
pycartan.egg-info/requires.txt
pycartan.egg-info/top_level.txt