Metadata-Version: 1.0
Name: pycartan
Version: 0.1.5
Summary: Python library for (vector) differential forms in control theory
Home-page: https://github.com/TUD-RST/pycartan
Author: Carsten Knoll, Klemens Fritzsche, Torsten Knüppel
Author-email: Carsten.Knoll@tu-dresden.de
License: BSD3
Keywords: differential forms,wedge product,exterior derivative,frobenius theorem,differential flat systems
Platform: UNKNOWN
